{
  "name": "tpcds-06667g-wsales",
  "data": "/root/lihan/train_dataset/tpcds_0.6667g/web_sales.csv",
  "categorical_columns": [
    "ws_promo_sk"
  ],
  "numeric_columns": [
    "ws_wholesale_cost",
    "ws_list_price"
  ],
  "label_columns": [
    "ws_promo_sk"
  ],
  "bucket_columns": [
  ],
  "categorical_encoding": "binary",
  "numeric_encoding": "gaussian",
  "max_clusters": 5,
  "model_type": "torch_cvae",
  "lr": 0.001,
  "optimizer_type": "adam",
  "loss_agg_type": "mean",
  "gpu_num": 0,
  "epochs": 100,
  "batch_size": 128,
  "latent_dim": 100,
  "intermediate_dim": 150,
  "train_flag": "load",
  "operation": "aqp",
  "sample_method": "statistics",
  "sample_rate": 0.1,
  "sample_for_train": 1,
  "header": 1,
  "delimiter": ","
}
